mcp_server_seekr/__init__.py
mcp_server_seekr/main.py
mcp_server_seekr/seekr_types/__init__.py
mcp_server_seekr/seekr_types/seekr.py
mcp_server_seekr/services/__init__.py
mcp_server_seekr/services/seekr_client.py
mcp_server_seekr/tools/__init__.py
mcp_server_seekr/tools/query_tool.py
mcp_server_seekr-0.15.1.dist-info/licenses/LICENSE
mcp_server_seekr-0.15.1.dist-info/METADATA
mcp_server_seekr-0.15.1.dist-info/WHEEL
mcp_server_seekr-0.15.1.dist-info/entry_points.txt
mcp_server_seekr-0.15.1.dist-info/top_level.txt
mcp_server_seekr-0.15.1.dist-info/RECORD
