Metadata-Version: 2.4
Name: mcp-server-seekr
Version: 0.15.1
Summary: MCP server implementation that provides web search capabilities via Seekr API
Home-page: https://github.com/seekr-sh/mcp-server-seekr
Author: Danilo Falcão
Author-email: Danilo Falcão <danilo@falcao.org>
License: MIT
Project-URL: Homepage, https://github.com/seekr-sh/mcp-server-seekr
Project-URL: Bug Reports, https://github.com/seekr-sh/mcp-server-seekr/issues
Project-URL: Source, https://github.com/seekr-sh/mcp-server-seekr
Keywords: mcp,seekr,search,scrape,claude,claude-desktop,modelcontextprotocol
Classifier: Development Status :: 4 - Beta
Classifier: Intended Audience :: Developers
Classifier: License :: OSI Approved :: MIT License
Classifier: Operating System :: OS Independent
Classifier: Programming Language :: Python :: 3
Classifier: Programming Language :: Python :: 3.10
Classifier: Programming Language :: Python :: 3.11
Classifier: Programming Language :: Python :: 3.12
Classifier: Topic :: Internet :: WWW/HTTP :: Indexing/Search
Classifier: Topic :: Software Development :: Libraries :: Python Modules
Requires-Python: >=3.10
License-File: LICENSE
Requires-Dist: fastmcp>=0.1.0
Requires-Dist: httpx>=0.27.0
Requires-Dist: pydantic>=2.0.0
Requires-Dist: python-dotenv>=1.0.0
Provides-Extra: dev
Requires-Dist: pytest>=7.0.0; extra == "dev"
Requires-Dist: pytest-asyncio>=0.21.0; extra == "dev"
Requires-Dist: pytest-cov>=4.0.0; extra == "dev"
Requires-Dist: black>=23.0.0; extra == "dev"
Requires-Dist: ruff>=0.1.0; extra == "dev"
Requires-Dist: mypy>=1.0.0; extra == "dev"
Dynamic: author
Dynamic: home-page
Dynamic: license-file
Dynamic: requires-python
